[
  {
    "modulus": 5,
    "slope": 3,
    "intercept": 2,
    "found_rule": true,
    "convergence_type": "phase_transition",
    "agents_correct": 6,
    "best_ratio": 0.0299,
    "mean_ratio": 0.0299,
    "discovery_step": 250,
    "discovery_expression": "((t * 3) + 2)",
    "stream_length_used": 1500,
    "consensus_threshold_used": 0.4,
    "beam_width_used": 25
  },
  {
    "modulus": 7,
    "slope": 4,
    "intercept": 3,
    "found_rule": true,
    "convergence_type": "phase_transition",
    "agents_correct": 6,
    "best_ratio": 0.0247,
    "mean_ratio": 0.0247,
    "discovery_step": 250,
    "discovery_expression": "(((t * 4) + 3) + 7)",
    "stream_length_used": 1500,
    "consensus_threshold_used": 0.4,
    "beam_width_used": 25
  },
  {
    "modulus": 11,
    "slope": 6,
    "intercept": 4,
    "found_rule": true,
    "convergence_type": "phase_transition",
    "agents_correct": 6,
    "best_ratio": 0.02,
    "mean_ratio": 0.02,
    "discovery_step": 250,
    "discovery_expression": "(0 + (4 + (t * 6)))",
    "stream_length_used": 1500,
    "consensus_threshold_used": 0.4,
    "beam_width_used": 25
  },
  {
    "modulus": 13,
    "slope": 7,
    "intercept": 5,
    "found_rule": true,
    "convergence_type": "gradual",
    "agents_correct": 6,
    "best_ratio": 0.0528,
    "mean_ratio": 0.0528,
    "discovery_step": null,
    "discovery_expression": null,
    "stream_length_used": 2500,
    "consensus_threshold_used": 0.35,
    "beam_width_used": 30
  },
  {
    "modulus": 17,
    "slope": 9,
    "intercept": 6,
    "found_rule": true,
    "convergence_type": "gradual",
    "agents_correct": 6,
    "best_ratio": 0.0475,
    "mean_ratio": 0.0475,
    "discovery_step": null,
    "discovery_expression": null,
    "stream_length_used": 3500,
    "consensus_threshold_used": 0.3,
    "beam_width_used": 35
  }
]